{
  "cases": [
    {
      "id": 1,
      "client": "株式会社リクルート 様",
      "industry": "IT・ソフトウェア",
      "title": "モバイル総合サポート LINE公式アカウント運用",
      "image": "/img/2.jpg",
      "services": ["LINE公式運用", "Lステップ構築"]
    },
    {
      "id": 2,
      "client": "株式会社みずほフィナンシャル 様",
      "industry": "金融・保険",
      "title": "CRM × Lステップ連携による業務自動化",
      "image": "/img/4.jpg",
      "services": ["RPA導入", "業務自動化", "CRM連携"]
    },
    {
      "id": 3,
      "client": "北海道ハウジング 様",
      "industry": "不動産",
      "title": "地域密着型の物件仲介サポート導入",
      "image": "/img/6.jpg",
      "services": ["集客支援", "内覧予約自動化"]
    },
    {
      "id": 4,
      "client": "全国チェーン小売A社 様",
      "industry": "小売・EC",
      "title": "コールセンター立ち上げから定着までの伴走支援",
      "image": "/img/1.jpg",
      "services": ["コールセンター構築", "研修設計", "KPI運用"]
    },
    {
      "id": 5,
      "client": "飲食チェーンB社 様",
      "industry": "飲食・サービス",
      "title": "LINE会員プログラム導入によるリピート施策",
      "image": "/img/5.jpg",
      "services": ["LINE公式運用", "CRM連携"]
    },
    {
      "id": 6,
      "client": "教育サービスC社 様",
      "industry": "教育・人材",
      "title": "資料請求〜クロージングの自動ナーチャリング",
      "image": "/img/8.jpg",
      "services": ["Lステップ構築", "ステップ配信設計"]
    },
    {
      "id": 7,
      "client": "医療法人D会 様",
      "industry": "医療・ヘルスケア",
      "title": "予約管理と受付業務のRPA化",
      "image": "/img/7.jpg",
      "services": ["RPA導入", "業務自動化"]
    },
    {
      "id": 8,
      "client": "地方自治体E 様",
      "industry": "官公庁・自治体",
      "title": "住民向けコールセンター受託運用",
      "image": "/img/3.jpg",
      "services": ["コールセンター運用", "KPI運用"]
    }
  ]
}
